Workbook

Sheet Dashboard
A1: FY2011 Revenue Variance — Plan vs Actual (by market)
A2: Finding: 2011 revenue grew ~2% year-over-year but landed ~10% below a +10% growth plan. The gap is almost entirely a volume shortfall (the growth assumption was too aggressive); better-than-planned pricing cushioned it. Like-for-like Jan–Nov — December 2011 is truncated in the source and excluded.
J3: Helper tables (drive the charts)
A4: Budget revenue | C4: Actual revenue | E4: Total variance | G4: Variance % | J4: Step | K4: Value | L4: CumEnd | M4: Base | N4: Decrease | O4: Increase | P4: Total
A5: =Model!F21 -> 10243854 | C5: =Model!C31 -> 9204145.7 | E5: =Model!C31-Model!F21 -> -1039707.9 | G5: =(Model!C31-Model!F21)/Model!F21 -> -0.10149578 | J5: Budget | K5: =Model!B34 -> 10243854 | L5: =K5 -> 10243854 | M5: 0 | N5: 0 | O5: 0 | P5: =K5 -> 10243854
J6: Volume | K6: =Model!B35 -> -1482277.8 | L6: =L5+K6 -> 8761575.8 | M6: =L6-MAX(K6,0) -> 8761575.8 | N6: =MAX(-K6,0) -> 1482277.8 | O6: =MAX(K6,0) -> 0 | P6: 0
J7: Mix | K7: =Model!B36 -> 120504.94 | L7: =L6+K7 -> 8882080.7 | M7: =L7-MAX(K7,0) -> 8761575.8 | N7: =MAX(-K7,0) -> 0 | O7: =MAX(K7,0) -> 120504.94 | P7: 0
J8: Price | K8: =Model!B37 -> 322064.97 | L8: =L7+K8 -> 9204145.7 | M8: =L8-MAX(K8,0) -> 8882080.7 | N8: =MAX(-K8,0) -> 0 | O8: =MAX(K8,0) -> 322064.97 | P8: 0
J9: Actual | K9: =Model!B38 -> 9204145.7 | L9: =K9 -> 9204145.7 | M9: 0 | N9: 0 | O9: 0 | P9: =K9 -> 9204145.7
J12: Month | K12: Budget | L12: Actual
J13: 1 | K13: =SUMIFS(Data!$E:$E,Data!$A:$A,Assumptions!$B$3,Data!$B:$B,J13)*(Model!$F$21/Model!$C$11) -> 739518.73 | L13: =SUMIFS(Data!$E:$E,Data!$A:$A,Assumptions!$B$4,Data!$B:$B,J13) -> 691364.56
J14: 2 | K14: =SUMIFS(Data!$E:$E,Data!$A:$A,Assumptions!$B$3,Data!$B:$B,J14)*(Model!$F$21/Model!$C$11) -> 626933.93 | L14: =SUMIFS(Data!$E:$E,Data!$A:$A,Assumptions!$B$4,Data!$B:$B,J14) -> 523631.89
J15: 3 | K15: =SUMIFS(Data!$E:$E,Data!$A:$A,Assumptions!$B$3,Data!$B:$B,J15)*(Model!$F$21/Model!$C$11) -> 944434.96 | L15: =SUMIFS(Data!$E:$E,Data!$A:$A,Assumptions!$B$4,Data!$B:$B,J15) -> 717639.36
J16: 4 | K16: =SUMIFS(Data!$E:$E,Data!$A:$A,Assumptions!$B$3,Data!$B:$B,J16)*(Model!$F$21/Model!$C$11) -> 772172.35 | L16: =SUMIFS(Data!$E:$E,Data!$A:$A,Assumptions!$B$4,Data!$B:$B,J16) -> 537808.62
J17: 5 | K17: =SUMIFS(Data!$E:$E,Data!$A:$A,Assumptions!$B$3,Data!$B:$B,J17)*(Model!$F$21/Model!$C$11) -> 747620.09 | L17: =SUMIFS(Data!$E:$E,Data!$A:$A,Assumptions!$B$4,Data!$B:$B,J17) -> 770536.02
J18: 6 | K18: =SUMIFS(Data!$E:$E,Data!$A:$A,Assumptions!$B$3,Data!$B:$B,J18)*(Model!$F$21/Model!$C$11) -> 852322.07 | L18: =SUMIFS(Data!$E:$E,Data!$A:$A,Assumptions!$B$4,Data!$B:$B,J18) -> 761739.9
J19: 7 | K19: =SUMIFS(Data!$E:$E,Data!$A:$A,Assumptions!$B$3,Data!$B:$B,J19)*(Model!$F$21/Model!$C$11) -> 737257.76 | L19: =SUMIFS(Data!$E:$E,Data!$A:$A,Assumptions!$B$4,Data!$B:$B,J19) -> 719221.19
J20: 8 | K20: =SUMIFS(Data!$E:$E,Data!$A:$A,Assumptions!$B$3,Data!$B:$B,J20)*(Model!$F$21/Model!$C$11) -> 790012.47 | L20: =SUMIFS(Data!$E:$E,Data!$A:$A,Assumptions!$B$4,Data!$B:$B,J20) -> 759138.38
J21: 9 | K21: =SUMIFS(Data!$E:$E,Data!$A:$A,Assumptions!$B$3,Data!$B:$B,J21)*(Model!$F$21/Model!$C$11) -> 1047269.3 | L21: =SUMIFS(Data!$E:$E,Data!$A:$A,Assumptions!$B$4,Data!$B:$B,J21) -> 1058590.2
J22: 10 | K22: =SUMIFS(Data!$E:$E,Data!$A:$A,Assumptions!$B$3,Data!$B:$B,J22)*(Model!$F$21/Model!$C$11) -> 1320493.3 | L22: =SUMIFS(Data!$E:$E,Data!$A:$A,Assumptions!$B$4,Data!$B:$B,J22) -> 1154979.3
J23: 11 | K23: =SUMIFS(Data!$E:$E,Data!$A:$A,Assumptions!$B$3,Data!$B:$B,J23)*(Model!$F$21/Model!$C$11) -> 1665818.7 | L23: =SUMIFS(Data!$E:$E,Data!$A:$A,Assumptions!$B$4,Data!$B:$B,J23) -> 1509496.3

Sheet Model
A1: Calculation engine — Base → Budget → Actual → Price/Volume/Mix bridge
A2: All figures are Jan–Nov (like-for-like). Segment = market.
A3: 1. Base year actuals (Jan–Nov, = Assumptions base year)
A4: Market | B4: Units | C4: Revenue | D4: Avg Price
A5: United Kingdom | B5: =SUMIFS(Data!$D:$D,Data!$A:$A,Assumptions!$B$3,Data!$C:$C,$A5,Data!$B:$B,"<=11") -> 4170870 | C5: =SUMIFS(Data!$E:$E,Data!$A:$A,Assumptions!$B$3,Data!$C:$C,$A5,Data!$B:$B,"<=11") -> 7690357 | D5: =C5/B5 -> 1.8438256
A6: EIRE | B6: =SUMIFS(Data!$D:$D,Data!$A:$A,Assumptions!$B$3,Data!$C:$C,$A6,Data!$B:$B,"<=11") -> 179977 | C6: =SUMIFS(Data!$E:$E,Data!$A:$A,Assumptions!$B$3,Data!$C:$C,$A6,Data!$B:$B,"<=11") -> 355595.3 | D6: =C6/B6 -> 1.9757819
A7: Netherlands | B7: =SUMIFS(Data!$D:$D,Data!$A:$A,Assumptions!$B$3,Data!$C:$C,$A7,Data!$B:$B,"<=11") -> 172697 | C7: =SUMIFS(Data!$E:$E,Data!$A:$A,Assumptions!$B$3,Data!$C:$C,$A7,Data!$B:$B,"<=11") -> 253388.67 | D7: =C7/B7 -> 1.4672442
A8: Germany | B8: =SUMIFS(Data!$D:$D,Data!$A:$A,Assumptions!$B$3,Data!$C:$C,$A8,Data!$B:$B,"<=11") -> 101279 | C8: =SUMIFS(Data!$E:$E,Data!$A:$A,Assumptions!$B$3,Data!$C:$C,$A8,Data!$B:$B,"<=11") -> 186614.39 | D8: =C8/B8 -> 1.8425773
A9: France | B9: =SUMIFS(Data!$D:$D,Data!$A:$A,Assumptions!$B$3,Data!$C:$C,$A9,Data!$B:$B,"<=11") -> 156306 | C9: =SUMIFS(Data!$E:$E,Data!$A:$A,Assumptions!$B$3,Data!$C:$C,$A9,Data!$B:$B,"<=11") -> 134399.38 | D9: =C9/B9 -> 0.85984786
A10: Other | B10: =SUMIFS(Data!$D:$D,Data!$A:$A,Assumptions!$B$3,Data!$C:$C,$A10,Data!$B:$B,"<=11") -> 442859 | C10: =SUMIFS(Data!$E:$E,Data!$A:$A,Assumptions!$B$3,Data!$C:$C,$A10,Data!$B:$B,"<=11") -> 420998.84 | D10: =C10/B10 -> 0.95063856
A11: Total | B11: =SUM(B5:B10) -> 5223988 | C11: =SUM(C5:C10) -> 9041353.6 | D11: =C11/B11 -> 1.7307378
A13: 2. Budget (base × plan assumptions)
A14: Market | B14: Vol Gr % | C14: Price Ch % | D14: Bud Units | E14: Bud Price | F14: Bud Revenue
A15: =A5 -> United Kingdom | B15: =Assumptions!B9 -> 0.1 | C15: =Assumptions!C9 -> 0.03 | D15: =B5*(1+B15) -> 4587957 | E15: =D5*(1+C15) -> 1.8991404 | F15: =D15*E15 -> 8713174.5
A16: =A6 -> EIRE | B16: =Assumptions!B10 -> 0.1 | C16: =Assumptions!C10 -> 0.03 | D16: =B6*(1+B16) -> 197974.7 | E16: =D6*(1+C16) -> 2.0350554 | F16: =D16*E16 -> 402889.47
A17: =A7 -> Netherlands | B17: =Assumptions!B11 -> 0.1 | C17: =Assumptions!C11 -> 0.03 | D17: =B7*(1+B17) -> 189966.7 | E17: =D7*(1+C17) -> 1.5112615 | F17: =D17*E17 -> 287089.36
A18: =A8 -> Germany | B18: =Assumptions!B12 -> 0.1 | C18: =Assumptions!C12 -> 0.03 | D18: =B8*(1+B18) -> 111406.9 | E18: =D8*(1+C18) -> 1.8978547 | F18: =D18*E18 -> 211434.1
A19: =A9 -> France | B19: =Assumptions!B13 -> 0.1 | C19: =Assumptions!C13 -> 0.03 | D19: =B9*(1+B19) -> 171936.6 | E19: =D9*(1+C19) -> 0.8856433 | F19: =D19*E19 -> 152274.5
A20: =A10 -> Other | B20: =Assumptions!B14 -> 0.1 | C20: =Assumptions!C14 -> 0.03 | D20: =B10*(1+B20) -> 487144.9 | E20: =D10*(1+C20) -> 0.97915771 | F20: =D20*E20 -> 476991.69
A21: Total | D21: =SUM(D15:D20) -> 5746386.8 | F21: =SUM(F15:F20) -> 10243854
A23: 3. Actual (Jan–Nov, = Assumptions budget year) + per-segment effects
A24: Market | B24: Act Units | C24: Act Revenue | D24: Act Price | E24: Mix effect | F24: Price effect
A25: =A5 -> United Kingdom | B25: =SUMIFS(Data!$D:$D,Data!$A:$A,Assumptions!$B$4,Data!$C:$C,$A25,Data!$B:$B,"<=11") -> 4060964 | C25: =SUMIFS(Data!$E:$E,Data!$A:$A,Assumptions!$B$4,Data!$C:$C,$A25,Data!$B:$B,"<=11") -> 7684331 | D25: =C25/B25 -> 1.8922431 | E25: =(B25-D15*($B$31/$D$21))*E15 -> 259956.03 | F25: =(D25-E15)*B25 -> -28009.806
A26: =A6 -> EIRE | B26: =SUMIFS(Data!$D:$D,Data!$A:$A,Assumptions!$B$4,Data!$C:$C,$A26,Data!$B:$B,"<=11") -> 137281 | C26: =SUMIFS(Data!$E:$E,Data!$A:$A,Assumptions!$B$4,Data!$C:$C,$A26,Data!$B:$B,"<=11") -> 266079.81 | D26: =C26/B26 -> 1.9382129 | E26: =(B26-D16*($B$31/$D$21))*E16 -> -65217.239 | F26: =(D26-E16)*B26 -> -13294.625
A27: =A7 -> Netherlands | B27: =SUMIFS(Data!$D:$D,Data!$A:$A,Assumptions!$B$4,Data!$C:$C,$A27,Data!$B:$B,"<=11") -> 185592 | C27: =SUMIFS(Data!$E:$E,Data!$A:$A,Assumptions!$B$4,Data!$C:$C,$A27,Data!$B:$B,"<=11") -> 264933.84 | D27: =C27/B27 -> 1.4275068 | E27: =(B27-D17*($B$31/$D$21))*E17 -> 34930.297 | F27: =(D27-E17)*B27 -> -15544.207
A28: =A8 -> Germany | B28: =SUMIFS(Data!$D:$D,Data!$A:$A,Assumptions!$B$4,Data!$C:$C,$A28,Data!$B:$B,"<=11") -> 108378 | C28: =SUMIFS(Data!$E:$E,Data!$A:$A,Assumptions!$B$4,Data!$C:$C,$A28,Data!$B:$B,"<=11") -> 205641.83 | D28: =C28/B28 -> 1.8974499 | E28: =(B28-D18*($B$31/$D$21))*E18 -> 24845.942 | F28: =(D28-E18)*B28 -> -43.861903
A29: =A9 -> France | B29: =SUMIFS(Data!$D:$D,Data!$A:$A,Assumptions!$B$4,Data!$C:$C,$A29,Data!$B:$B,"<=11") -> 103329 | C29: =SUMIFS(Data!$E:$E,Data!$A:$A,Assumptions!$B$4,Data!$C:$C,$A29,Data!$B:$B,"<=11") -> 192821.88 | D29: =C29/B29 -> 1.8660964 | E29: =(B29-D19*($B$31/$D$21))*E19 -> -38727.857 | F29: =(D29-E19)*B29 -> 101309.24
A30: =A10 -> Other | B30: =SUMIFS(Data!$D:$D,Data!$A:$A,Assumptions!$B$4,Data!$C:$C,$A30,Data!$B:$B,"<=11") -> 319345 | C30: =SUMIFS(Data!$E:$E,Data!$A:$A,Assumptions!$B$4,Data!$C:$C,$A30,Data!$B:$B,"<=11") -> 590337.35 | D30: =C30/B30 -> 1.848588 | E30: =(B30-D20*($B$31/$D$21))*E20 -> -95282.232 | F30: =(D30-E20)*B30 -> 277648.23
A31: Total | B31: =SUM(B25:B30) -> 4914889 | C31: =SUM(C25:C30) -> 9204145.7 | E31: =SUM(E25:E30) -> 120504.94 | F31: =SUM(F25:F30) -> 322064.97
A33: 4. Revenue bridge: Budget → Volume → Mix → Price → Actual
A34: Budget revenue | B34: =F21 -> 10243854
A35: Volume effect | B35: =(B31-D21)*(F21/D21) -> -1482277.8
A36: Mix effect | B36: =E31 -> 120504.94
A37: Price effect | B37: =F31 -> 322064.97
A38: Actual revenue | B38: =C31 -> 9204145.7
A39: Total variance | B39: =C31-F21 -> -1039707.9
A40: Bridge check (≈0) | B40: =(C31-F21)-(B35+B36+B37) -> 0

Sheet Assumptions
A1: FP&A Variance Model — Assumptions (the plan, set in advance)
A3: Base year (actuals the plan is built from) | B3: 2010
A4: Budget year (plan vs actual compared) | B4: 2011
A6: Blue / shaded cells are inputs. Change them and the whole model + bridge update.
A7: Comparison is like-for-like Jan–Nov (December 2011 is truncated in the source, so it is excluded).
A8: Market segment | B8: Volume Growth % | C8: Price Change %
A9: United Kingdom | B9: 0.1 | C9: 0.03
A10: EIRE | B10: 0.1 | C10: 0.03
A11: Netherlands | B11: 0.1 | C11: 0.03
A12: Germany | B12: 0.1 | C12: 0.03
A13: France | B13: 0.1 | C13: 0.03
A14: Other | B14: 0.1 | C14: 0.03

Sheet Data
A1: MONTHLY FACT TABLE — output of sql/build_fact_table_by_market.sql (DuckDB)
A2: Imported from the data pipeline (real Online Retail II). Re-run the SQL to refresh; do not edit by hand.
A4: year | B4: month | C4: category | D4: units | E4: revenue | F4: avg_price
A5: 2009 | B5: 12 | C5: EIRE | D5: 9414 | E5: 20099.74 | F5: 2.1351
A6: 2009 | B6: 12 | C6: France | D6: 3688 | E6: 6521.69 | F6: 1.7684
A7: 2009 | B7: 12 | C7: Germany | D7: 4828 | E7: 10096.85 | F7: 2.0913
A8: 2009 | B8: 12 | C8: Netherlands | D8: 10822 | E8: 15204.73 | F8: 1.405
A9: 2009 | B9: 12 | C9: Other | D9: 10417 | E9: 23445.53 | F9: 2.2507
A10: 2009 | B10: 12 | C10: United Kingdom | D10: 387812 | E10: 750317.22 | F10: 1.9347
A11: 2010 | B11: 1 | C11: EIRE | D11: 30809 | E11: 65258.43 | F11: 2.1182
A12: 2010 | B12: 1 | C12: France | D12: 5313 | E12: 8465.63 | F12: 1.5934
A13: 2010 | B13: 1 | C13: Germany | D13: 6321 | E13: 12562.11 | F13: 1.9874
A14: 2010 | B14: 1 | C14: Netherlands | D14: 20531 | E14: 29230.77 | F14: 1.4237
A15: 2010 | B15: 1 | C15: Other | D15: 70993 | E15: 25393.9 | F15: 0.3577
A16: 2010 | B16: 1 | C16: United Kingdom | D16: 257558 | E16: 511797.66 | F16: 1.9871
... A154: 2011 | B154: 12 | C154: United Kingdom | D154: 287266 | E154: 592622.09 | F154: 2.063

Sheet Notes
A1: Methodology & Notes
A3: DATA SOURCE
A4: • UCI 'Online Retail II' — real UK online-retail transactions, Dec 2009 – Dec 2011 (~1.07M rows).
A5: • Pipeline: sql/build_fact_table_by_market.sql (DuckDB).
A7: CLEANING (Stage 2 profiling on 1,067,371 raw rows)
A8: • Dropped cancellations ('C' invoices), non-positive quantities, and non-positive prices (~2.4%).
A9: • Kept 1,041,670 rows (97.6%). Missing Customer IDs (243,007) retained — revenue does not need them.
A11: SEGMENTATION (v1 'by market' cut)
A12: • Segment = market: United Kingdom + EIRE, Netherlands, Germany, France, and 'Other' (all remaining countries).
A13: • The UK is ~85% of revenue, so cross-market mix is a minor variance driver by construction.
A14: • A v2 'by product category' cut (derived from descriptions) would show a richer mix story.
A16: COMPARISON PERIOD
... A32: • Change the Assumptions and the variance — and the story — change accordingly.
